ProfiTrade/__init__.py
ProfiTrade/Analysis/Fundemental.py
ProfiTrade/Analysis/Technical.py
ProfiTrade/Analysis/__init__.py
ProfiTrade/Data/Financial.py
ProfiTrade/Data/Price.py
ProfiTrade/Data/__init__.py
ProfiTrade/Indicators/Fundemental.py
ProfiTrade/Indicators/Technical.py
ProfiTrade/Indicators/__init__.py
ProfiTrade/Log/__init__.py
ProfiTrade/Log/csvLog.py
ProfiTrade/Screen/Catalyst.py
ProfiTrade/Screen/__init__.py
ProfiTrade/Screen/Finviz/Quantitative.py
ProfiTrade/Screen/Finviz/Technical.py
ProfiTrade/Screen/Finviz/__init__.py
ProfiTrade-0.1.1.dist-info/LICENSE.txt
ProfiTrade-0.1.1.dist-info/METADATA
ProfiTrade-0.1.1.dist-info/WHEEL
ProfiTrade-0.1.1.dist-info/top_level.txt
ProfiTrade-0.1.1.dist-info/RECORD
